spsgamepkg/__init__.py
spsgamepkg/game.py
spsgamepkg-0.0.2.dist-info/LICENSE
spsgamepkg-0.0.2.dist-info/METADATA
spsgamepkg-0.0.2.dist-info/WHEEL
spsgamepkg-0.0.2.dist-info/top_level.txt
spsgamepkg-0.0.2.dist-info/RECORD
