Metadata-Version: 2.1
Name: spsgamepkg
Version: 0.0.2
Summary: Stone Paper Scissors - a basic program to play rock,paper,scissors with PC
Author-email: Aswin Venkat <aswinvenk8@gmail.com>
Project-URL: Homepage, https://github.com/aswinvenk/stonepaperscissors
Project-URL: Bug Tracker, https://github.com/aswinvenk/stonepaperscissors/issues
Classifier: Programming Language :: Python :: 3
Classifier: License :: OSI Approved :: MIT License
Classifier: Operating System :: OS Independent
Requires-Python: >=3.7
License-File: LICENSE
